teamdbapi/__init__.py
teamdbapi/api_client.py
teamdbapi/configuration.py
teamdbapi/rest.py
teamdbapi/api/__init__.py
teamdbapi/api/assembly_api.py
teamdbapi/api/car_api.py
teamdbapi/api/component_api.py
teamdbapi/api/config_api.py
teamdbapi/api/criteria_api.py
teamdbapi/api/edit_api.py
teamdbapi/api/event_api.py
teamdbapi/api/fixed_field_api.py
teamdbapi/api/group_api.py
teamdbapi/api/import_export_api.py
teamdbapi/api/issue_api.py
teamdbapi/api/lap_api.py
teamdbapi/api/lap_report_api.py
teamdbapi/api/model_field_api.py
teamdbapi/api/mounting_api.py
teamdbapi/api/notes_authorization_api.py
teamdbapi/api/overall_api.py
teamdbapi/api/parameter_api.py
teamdbapi/api/parameter_binding_api.py
teamdbapi/api/part_api.py
teamdbapi/api/report_api.py
teamdbapi/api/revision_api.py
teamdbapi/api/revision_editor_selector_api.py
teamdbapi/api/run_api.py
teamdbapi/api/script_api.py
teamdbapi/api/session_api.py
teamdbapi/api/target_api.py
teamdbapi/api/team_db_list_api.py
teamdbapi/api/team_db_view_api.py
teamdbapi/api/tire_api.py
teamdbapi/api/tire_set_api.py
teamdbapi/api/track_api.py
teamdbapi/api/track_layout_api.py
teamdbapi/api/update_request_api.py
teamdbapi/api/user_api.py
teamdbapi/api/value_field_api.py
teamdbapi/api/version_api.py
teamdbapi/models/__init__.py
teamdbapi/models/add_part_car_parameter_arg.py
teamdbapi/models/assembly.py
teamdbapi/models/bleed_adjustment.py
teamdbapi/models/calibration.py
teamdbapi/models/car.py
teamdbapi/models/car_parameters_context.py
teamdbapi/models/compare_options.py
teamdbapi/models/compare_result.py
teamdbapi/models/compare_result_detail.py
teamdbapi/models/component.py
teamdbapi/models/copy_from_tags_args.py
teamdbapi/models/couple_guid_text.py
teamdbapi/models/criteria.py
teamdbapi/models/criteria_set.py
teamdbapi/models/criteria_value.py
teamdbapi/models/criteria_value_detail.py
teamdbapi/models/event.py
teamdbapi/models/file_revision_info.py
teamdbapi/models/fixed_field.py
teamdbapi/models/group.py
teamdbapi-3.11.0.dist-info/licenses/LICENSE
teamdbapi-3.11.0.dist-info/WHEEL
teamdbapi-3.11.0.dist-info/METADATA
teamdbapi-3.11.0.dist-info/RECORD
