Metadata-Version: 2.4
Name: teamdbapi
Version: 3.11.0
Summary: Easily access the TeamDB Web API.
Keywords: teamdbapi,Trackside,Trackside Software,TeamDB
Author-email: Trackside Software <support@trackside.fr>
Requires-Python: >=3.4
Classifier: License :: OSI Approved :: MIT License
Classifier: Programming Language :: Python
Classifier: Programming Language :: Python :: 3
License-File: LICENSE
Requires-Dist: certifi >= 14.05.14
Requires-Dist: six >= 1.10
Requires-Dist: python_dateutil >= 2.5.3
Requires-Dist: setuptools >= 21.0.0
Requires-Dist: urllib3 >= 1.15.1
Project-URL: Home, https://www.tracksidesoftware.fr/teamdb
